<expression xsi:schemaLocation="http://www.imsglobal.org/xsd/imslorsltitm_v1p0 http://fire.eun.org/lode/imslorsltitm_v1p0.xsd" xmlns="http://www.imsglobal.org/xsd/imslorsltitm_v1p0" xmlns:xsi="http://www.w3.org/2001/XMLSchema-instance">
  <identifier>
    <catalog>hdl</catalog>
    <entry>10494/29907</entry>
  </identifier>
  <identifier>
    <catalog>expression-cmr-id</catalog>
    <entry>29907</entry>
  </identifier>
  <identifier>
    <catalog>IML-MMB</catalog>
    <entry>522676</entry>
  </identifier>
  <description>
    <facet>
      <vocabularyID>LRE.expressionDescriptionFacetValues</vocabularyID>
      <value>main</value>
    </facet>
    <metadata>
      <schema>http://ltsc.ieee.org/xsd/LOM</schema>
      <lom xsi:schemaLocation="http://ltsc.ieee.org/xsd/LOM http://ltsc.ieee.org/xsd/lomv1.0/lomLoose.xsd" xmlns="http://ltsc.ieee.org/xsd/LOM">
        <general>
          <identifier>
            <catalog>oai</catalog>
            <entry>oai:spindeln.iml.umu.se:522676</entry>
          </identifier>
          <identifier>
            <catalog>IML-MMB</catalog>
            <entry>522676</entry>
          </identifier>
          <title>
            <string language="sv">Kebabkött på spett</string>
            <string language="en">Kebab meat on spit</string>
            <string language="x-mt-de">Kebab Fleisch auf Spit</string>
            <string language="x-mt-fr">Viande de Kebab sur la broche</string>
            <string language="x-mt-pt">Carne de Kebab no cuspo</string>
            <string language="x-mt-it">Carne di Kebab sullo sputo</string>
            <string language="x-mt-el">Κρέας Kebab στον οβελό</string>
            <string language="x-mt-es">Carne de Kebab en escupida</string>
          </title>
          <language>x-none</language>
          <description>
            <string language="sv">Kebabkött grillas på spett.</string>
            <string language="en">Kebab meat is grilled on spit.</string>
          </description>
          <keyword>
            <string language="sv">kebab</string>
            <string language="en">kebab</string>
          </keyword>
          <keyword>
            <string language="sv">grilla</string>
            <string language="en">barbecue</string>
          </keyword>
          <keyword>
            <string language="sv">kött</string>
            <string language="en">meat</string>
          </keyword>
          <keyword>
            <string language="sv">snabbmat</string>
            <string language="en">fast food</string>
          </keyword>
          <keyword>
            <string language="sv">Kebabkött</string>
            <string language="en">kebab meat</string>
          </keyword>
          <description>
            <string language="x-mt-de">Kebab Fleisch wird auf Spit gegrillt.</string>
          </description>
          <description>
            <string language="x-mt-fr">De la viande de Kebab est grillée sur la broche.</string>
          </description>
          <description>
            <string language="x-mt-pt">A carne de Kebab é grelhada no cuspo.</string>
          </description>
          <description>
            <string language="x-mt-it">La carne di Kebab è cotta sullo sputo.</string>
          </description>
          <description>
            <string language="x-mt-el">Το κρέας Kebab ψήνεται στη σχάρα στον οβελό.</string>
          </description>
          <description>
            <string language="x-mt-es">La carne de Kebab se asa a la parilla en escupida.</string>
          </description>
          <keyword>
            <string language="x-mt-de">kebab</string>
          </keyword>
          <keyword>
            <string language="x-mt-de">Grill</string>
          </keyword>
          <keyword>
            <string language="x-mt-de">Fleisch</string>
          </keyword>
          <keyword>
            <string language="x-mt-de">Schnellimbiß</string>
          </keyword>
          <keyword>
            <string language="x-mt-de">kebab Fleisch</string>
          </keyword>
          <keyword>
            <string language="x-mt-fr">kebab</string>
          </keyword>
          <keyword>
            <string language="x-mt-fr">barbecue</string>
          </keyword>
          <keyword>
            <string language="x-mt-fr">viande</string>
          </keyword>
          <keyword>
            <string language="x-mt-fr">aliments de préparation rapide</string>
          </keyword>
          <keyword>
            <string language="x-mt-fr">viande de kebab</string>
          </keyword>
          <keyword>
            <string language="x-mt-pt">kebab</string>
          </keyword>
          <keyword>
            <string language="x-mt-pt">barbecue</string>
          </keyword>
          <keyword>
            <string language="x-mt-pt">carne</string>
          </keyword>
          <keyword>
            <string language="x-mt-pt">alimento rápido</string>
          </keyword>
          <keyword>
            <string language="x-mt-pt">carne do kebab</string>
          </keyword>
          <keyword>
            <string language="x-mt-it">kebab</string>
          </keyword>
          <keyword>
            <string language="x-mt-it">barbecue</string>
          </keyword>
          <keyword>
            <string language="x-mt-it">carne</string>
          </keyword>
          <keyword>
            <string language="x-mt-it">alimenti a rapida preparazione</string>
          </keyword>
          <keyword>
            <string language="x-mt-it">carne del kebab</string>
          </keyword>
          <keyword>
            <string language="x-mt-el">kebab</string>
          </keyword>
          <keyword>
            <string language="x-mt-el">σχάρα</string>
          </keyword>
          <keyword>
            <string language="x-mt-el">κρέας</string>
          </keyword>
          <keyword>
            <string language="x-mt-el">γρήγορα τρόφιμα</string>
          </keyword>
          <keyword>
            <string language="x-mt-el">kebab κρέας</string>
          </keyword>
          <keyword>
            <string language="x-mt-es">kebab</string>
          </keyword>
          <keyword>
            <string language="x-mt-es">barbacoa</string>
          </keyword>
          <keyword>
            <string language="x-mt-es">carne</string>
          </keyword>
          <keyword>
            <string language="x-mt-es">alimentos de preparación rápida</string>
          </keyword>
          <keyword>
            <string language="x-mt-es">carne del kebab</string>
          </keyword>
        </general>
        <lifeCycle>
          <contribute>
            <role>
              <source>LRE.roleValues</source>
              <value>publisher</value>
            </role>
            <entity>BEGIN:VCARD
VERSION:3.0
N:MSU
FN:MSU
ORG:MSU
END:VCARD</entity>
          </contribute>
        </lifeCycle>
        <educational>
          <learningResourceType>
            <source>LRE.learningResourceTypeValues</source>
            <value>image</value>
          </learningResourceType>
          <typicalAgeRange>
            <string language="x-t-lre">7-18</string>
          </typicalAgeRange>
        </educational>
        <rights>
          <cost>
            <source>costValues</source>
            <value>no</value>
          </cost>
          <copyrightAndOtherRestrictions>
            <source>copyrightAndOtherRestrictionsValues</source>
            <value>yes</value>
          </copyrightAndOtherRestrictions>
          <description>
            <string language="x-t-cc-url">http://creativecommons.org/licenses/by-nc-sa/3.0/</string>
            <string language="en">Creative Commons Attribution-Noncommercial-Share Alike 3.0</string>
          </description>
        </rights>
        <classification>
          <purpose>
            <source>purposeValues</source>
            <value>discipline</value>
          </purpose>
          <taxonPath>
            <source>
              <string language="x-none">LRE-0001</string>
            </source>
            <taxon>
              <id>632</id>
              <entry>
                <string language="en">image</string>
                <string language="sv">bild</string>
              </entry>
            </taxon>
          </taxonPath>
        </classification>
        <metaMetadata>
          <identifier>
            <catalog>oai</catalog>
            <entry>oai:spindeln.iml.umu.se:522676-1</entry>
          </identifier>
          <identifier>
            <catalog>IML-MMB</catalog>
            <entry>522676-1</entry>
          </identifier>
          <contribute>
            <entity>BEGIN:VCARD
VERSION:3.0
N:Iselow;Mikael
FN:Mikael Iselow
ORG:MMB
END:VCARD</entity>
            <role>
              <source>LRE.roleMetaValues</source>
              <value>creator</value>
            </role>
            <date>
              <dateTime>2008-07-03T01:39:41.0Z</dateTime>
            </date>
          </contribute>
          <language>sv</language>
          <contribute>
            <entity>BEGIN:VCARD
FN:Myndigheten för skolutveckling
N:Myndigheten för skolutveckling
ORG:Myndigheten för skolutveckling
VERSION:3.0
END:VCARD</entity>
            <role>
              <value>provider</value>
              <source>ASPECTv1.0</source>
            </role>
            <date>
              <dateTime>2010-04-26T05:52:50.55Z</dateTime>
            </date>
          </contribute>
        </metaMetadata>
      </lom>
    </metadata>
  </description>
  <manifestation>
    <identifier>
      <catalog>IML-MMB</catalog>
      <entry>522676</entry>
    </identifier>
    <name>
      <vocabularyID>LRE.manifestationNameValues</vocabularyID>
      <value>experience</value>
    </name>
    <parameter>
      <vocabularyID>MIME</vocabularyID>
      <value>image/jpeg</value>
    </parameter>
    <item>
      <location>
        <uri>http://vix.iml.umu.se/mmb/522676.jpg</uri>
      </location>
    </item>
  </manifestation>
</expression>
