{
    "TOS": {
        "submission_TOS": "http://www.learningregistry.org/tos/cc0/v0-5/"
    }, 
    "active": true, 
    "doc_type": "resource_data", 
    "doc_version": "0.21.0", 
    "identity": {
        "curator": "European School Net", 
        "owner": "European School Net", 
        "submitter": "Learning Registry", 
        "submitter_type": "agent"
    }, 
    "keys": [
        "EUN", 
        "LOM", 
        "lr-test-data", 
        "muskel", 
        "muscle", 
        "kropp", 
        "body", 
        "h\u00e4lsa", 
        "health", 
        "gym", 
        "gym", 
        "tr\u00e4ning", 
        "exercising", 
        "styrketr\u00e4ning", 
        "fitness training", 
        "tr\u00e4na", 
        "exercise", 
        "muskler", 
        "muscles", 
        "Muskel", 
        "K\u00f6rper", 
        "Gesundheit", 
        "Turnhalle", 
        "Trainieren", 
        "Eignungtraining", 
        "\u00dcbung", 
        "Muskeln", 
        "muscle", 
        "corps", 
        "sant\u00e9", 
        "salle de gymnastique", 
        "s'exercer", 
        "formation de forme physique", 
        "exercice", 
        "muscles", 
        "m\u00fasculo", 
        "corpo", 
        "sa\u00fade", 
        "gym", 
        "exercitar", 
        "treinamento da aptid\u00e3o", 
        "exerc\u00edcio", 
        "m\u00fasculos", 
        "muscolo", 
        "corpo", 
        "salute", 
        "gym", 
        "esercitarsi", 
        "addestramento di idoneit\u00e0", 
        "esercitazione", 
        "muscoli", 
        "\u03bc\u03c5\u03c2", 
        "\u03c3\u03ce\u03bc\u03b1", 
        "\u03c5\u03b3\u03b5\u03af\u03b1", 
        "\u03b3\u03c5\u03bc\u03bd\u03b1\u03c3\u03c4\u03b9\u03ba\u03ae", 
        "\u03ac\u03c3\u03ba\u03b7\u03c3\u03b7", 
        "\u03ba\u03b1\u03c4\u03ac\u03c1\u03c4\u03b9\u03c3\u03b7 \u03b9\u03ba\u03b1\u03bd\u03cc\u03c4\u03b7\u03c4\u03b1\u03c2", 
        "\u03ac\u03c3\u03ba\u03b7\u03c3\u03b7", 
        "\u03bc\u03cd\u03b5\u03c2", 
        "m\u00fasculo", 
        "cuerpo", 
        "salud", 
        "gym", 
        "el ejercitar", 
        "entrenamiento de la aptitud", 
        "ejercicio", 
        "m\u00fasculos"
    ], 
    "payload_placement": "inline", 
    "payload_schema": [
        "LODE", 
        "LOM"
    ], 
    "resource_data": "<expression xsi:schemaLocation=\"http://www.imsglobal.org/xsd/imslorsltitm_v1p0 http://fire.eun.org/lode/imslorsltitm_v1p0.xsd\" xmlns=\"http://www.imsglobal.org/xsd/imslorsltitm_v1p0\" xmlns:xsi=\"http://www.w3.org/2001/XMLSchema-instance\">\r\n  <identifier>\r\n    <catalog>hdl</catalog>\r\n    <entry>10494/26008</entry>\r\n  </identifier>\r\n  <identifier>\r\n    <catalog>expression-cmr-id</catalog>\r\n    <entry>26008</entry>\r\n  </identifier>\r\n  <identifier>\r\n    <catalog>IML-MMB</catalog>\r\n    <entry>526350</entry>\r\n  </identifier>\r\n  <description>\r\n    <facet>\r\n      <vocabularyID>LRE.expressionDescriptionFacetValues</vocabularyID>\r\n      <value>main</value>\r\n    </facet>\r\n    <metadata>\r\n      <schema>http://ltsc.ieee.org/xsd/LOM</schema>\r\n      <lom xsi:schemaLocation=\"http://ltsc.ieee.org/xsd/LOM http://ltsc.ieee.org/xsd/lomv1.0/lomLoose.xsd\" xmlns=\"http://ltsc.ieee.org/xsd/LOM\">\r\n        <general>\r\n          <identifier>\r\n            <catalog>oai</catalog>\r\n            <entry>oai:spindeln.iml.umu.se:526350</entry>\r\n          </identifier>\r\n          <identifier>\r\n            <catalog>IML-MMB</catalog>\r\n            <entry>526350</entry>\r\n          </identifier>\r\n          <title>\r\n            <string language=\"sv\">Styrketr\u00e4ning</string>\r\n            <string language=\"en\">Weightlifting</string>\r\n            <string language=\"x-mt-de\">Weightlifting</string>\r\n            <string language=\"x-mt-fr\">Weightlifting</string>\r\n            <string language=\"x-mt-pt\">Weightlifting</string>\r\n            <string language=\"x-mt-it\">Weightlifting</string>\r\n            <string language=\"x-mt-el\">Weightlifting</string>\r\n            <string language=\"x-mt-es\">Weightlifting</string>\r\n          </title>\r\n          <language>x-none</language>\r\n          <description>\r\n            <string language=\"sv\">Ung man tr\u00e4nar muskler p\u00e5 ett gym.</string>\r\n            <string language=\"en\">A young man exercises his muscles in a gym.</string>\r\n          </description>\r\n          <keyword>\r\n            <string language=\"sv\">muskel</string>\r\n            <string language=\"en\">muscle</string>\r\n          </keyword>\r\n          <keyword>\r\n            <string language=\"sv\">kropp</string>\r\n            <string language=\"en\">body</string>\r\n          </keyword>\r\n          <keyword>\r\n            <string language=\"sv\">h\u00e4lsa</string>\r\n            <string language=\"en\">health</string>\r\n          </keyword>\r\n          <keyword>\r\n            <string language=\"sv\">gym</string>\r\n            <string language=\"en\">gym</string>\r\n          </keyword>\r\n          <keyword>\r\n            <string language=\"sv\">tr\u00e4ning</string>\r\n            <string language=\"en\">exercising</string>\r\n          </keyword>\r\n          <keyword>\r\n            <string language=\"sv\">styrketr\u00e4ning</string>\r\n            <string language=\"en\">fitness training</string>\r\n          </keyword>\r\n          <keyword>\r\n            <string language=\"sv\">tr\u00e4na</string>\r\n            <string language=\"en\">exercise</string>\r\n          </keyword>\r\n          <keyword>\r\n            <string language=\"sv\">muskler</string>\r\n            <string language=\"en\">muscles</string>\r\n          </keyword>\r\n          <description>\r\n            <string language=\"x-mt-de\">Ein junger Mann \u00fcbt seine Muskeln in einer \r\nTurnhalle aus.</string>\r\n          </description>\r\n          <description>\r\n            <string language=\"x-mt-fr\">Un jeune homme exerce ses muscles dans une salle \r\nde gymnastique.</string>\r\n          </description>\r\n          <description>\r\n            <string language=\"x-mt-pt\">Um homem novo exercita seus m\u00fasculos em um gym.</string>\r\n          </description>\r\n          <description>\r\n            <string language=\"x-mt-it\">Un giovane esercita i suoi muscoli in un gym.</string>\r\n          </description>\r\n          <description>\r\n            <string language=\"x-mt-el\">\u0388\u03bd\u03b1\u03c2 \u03bd\u03b5\u03b1\u03c1\u03cc\u03c2 \u03ac\u03bd\u03b4\u03c1\u03b1\u03c2 \u03b1\u03c3\u03ba\u03b5\u03af \u03c4\u03bf\u03c5\u03c2 \u03bc\u03c5\u03c2 \u03c4\u03bf\u03c5 \u03c3\u03b5 \u03bc\u03b9\u03b1 \r\n\u03b3\u03c5\u03bc\u03bd\u03b1\u03c3\u03c4\u03b9\u03ba\u03ae.</string>\r\n          </description>\r\n          <description>\r\n            <string language=\"x-mt-es\">Un hombre joven ejercita sus m\u00fasculos en un gym.</string>\r\n          </description>\r\n          <keyword>\r\n            <string language=\"x-mt-de\">Muskel</string>\r\n          </keyword>\r\n          <keyword>\r\n            <string language=\"x-mt-de\">K\u00f6rper</string>\r\n          </keyword>\r\n          <keyword>\r\n            <string language=\"x-mt-de\">Gesundheit</string>\r\n          </keyword>\r\n          <keyword>\r\n            <string language=\"x-mt-de\">Turnhalle</string>\r\n          </keyword>\r\n          <keyword>\r\n            <string language=\"x-mt-de\">Trainieren</string>\r\n          </keyword>\r\n          <keyword>\r\n            <string language=\"x-mt-de\">Eignungtraining</string>\r\n          </keyword>\r\n          <keyword>\r\n            <string language=\"x-mt-de\">\u00dcbung</string>\r\n          </keyword>\r\n          <keyword>\r\n            <string language=\"x-mt-de\">Muskeln</string>\r\n          </keyword>\r\n          <keyword>\r\n            <string language=\"x-mt-fr\">muscle</string>\r\n          </keyword>\r\n          <keyword>\r\n            <string language=\"x-mt-fr\">corps</string>\r\n          </keyword>\r\n          <keyword>\r\n            <string language=\"x-mt-fr\">sant\u00e9</string>\r\n          </keyword>\r\n          <keyword>\r\n            <string language=\"x-mt-fr\">salle de gymnastique</string>\r\n          </keyword>\r\n          <keyword>\r\n            <string language=\"x-mt-fr\">s'exercer</string>\r\n          </keyword>\r\n          <keyword>\r\n            <string language=\"x-mt-fr\">formation de forme physique</string>\r\n          </keyword>\r\n          <keyword>\r\n            <string language=\"x-mt-fr\">exercice</string>\r\n          </keyword>\r\n          <keyword>\r\n            <string language=\"x-mt-fr\">muscles</string>\r\n          </keyword>\r\n          <keyword>\r\n            <string language=\"x-mt-pt\">m\u00fasculo</string>\r\n          </keyword>\r\n          <keyword>\r\n            <string language=\"x-mt-pt\">corpo</string>\r\n          </keyword>\r\n          <keyword>\r\n            <string language=\"x-mt-pt\">sa\u00fade</string>\r\n          </keyword>\r\n          <keyword>\r\n            <string language=\"x-mt-pt\">gym</string>\r\n          </keyword>\r\n          <keyword>\r\n            <string language=\"x-mt-pt\">exercitar</string>\r\n          </keyword>\r\n          <keyword>\r\n            <string language=\"x-mt-pt\">treinamento da aptid\u00e3o</string>\r\n          </keyword>\r\n          <keyword>\r\n            <string language=\"x-mt-pt\">exerc\u00edcio</string>\r\n          </keyword>\r\n          <keyword>\r\n            <string language=\"x-mt-pt\">m\u00fasculos</string>\r\n          </keyword>\r\n          <keyword>\r\n            <string language=\"x-mt-it\">muscolo</string>\r\n          </keyword>\r\n          <keyword>\r\n            <string language=\"x-mt-it\">corpo</string>\r\n          </keyword>\r\n          <keyword>\r\n            <string language=\"x-mt-it\">salute</string>\r\n          </keyword>\r\n          <keyword>\r\n            <string language=\"x-mt-it\">gym</string>\r\n          </keyword>\r\n          <keyword>\r\n            <string language=\"x-mt-it\">esercitarsi</string>\r\n          </keyword>\r\n          <keyword>\r\n            <string language=\"x-mt-it\">addestramento di idoneit\u00e0</string>\r\n          </keyword>\r\n          <keyword>\r\n            <string language=\"x-mt-it\">esercitazione</string>\r\n          </keyword>\r\n          <keyword>\r\n            <string language=\"x-mt-it\">muscoli</string>\r\n          </keyword>\r\n          <keyword>\r\n            <string language=\"x-mt-el\">\u03bc\u03c5\u03c2</string>\r\n          </keyword>\r\n          <keyword>\r\n            <string language=\"x-mt-el\">\u03c3\u03ce\u03bc\u03b1</string>\r\n          </keyword>\r\n          <keyword>\r\n            <string language=\"x-mt-el\">\u03c5\u03b3\u03b5\u03af\u03b1</string>\r\n          </keyword>\r\n          <keyword>\r\n            <string language=\"x-mt-el\">\u03b3\u03c5\u03bc\u03bd\u03b1\u03c3\u03c4\u03b9\u03ba\u03ae</string>\r\n          </keyword>\r\n          <keyword>\r\n            <string language=\"x-mt-el\">\u03ac\u03c3\u03ba\u03b7\u03c3\u03b7</string>\r\n          </keyword>\r\n          <keyword>\r\n            <string language=\"x-mt-el\">\u03ba\u03b1\u03c4\u03ac\u03c1\u03c4\u03b9\u03c3\u03b7 \u03b9\u03ba\u03b1\u03bd\u03cc\u03c4\u03b7\u03c4\u03b1\u03c2</string>\r\n          </keyword>\r\n          <keyword>\r\n            <string language=\"x-mt-el\">\u03ac\u03c3\u03ba\u03b7\u03c3\u03b7</string>\r\n          </keyword>\r\n          <keyword>\r\n            <string language=\"x-mt-el\">\u03bc\u03cd\u03b5\u03c2</string>\r\n          </keyword>\r\n          <keyword>\r\n            <string language=\"x-mt-es\">m\u00fasculo</string>\r\n          </keyword>\r\n          <keyword>\r\n            <string language=\"x-mt-es\">cuerpo</string>\r\n          </keyword>\r\n          <keyword>\r\n            <string language=\"x-mt-es\">salud</string>\r\n          </keyword>\r\n          <keyword>\r\n            <string language=\"x-mt-es\">gym</string>\r\n          </keyword>\r\n          <keyword>\r\n            <string language=\"x-mt-es\">el ejercitar</string>\r\n          </keyword>\r\n          <keyword>\r\n            <string language=\"x-mt-es\">entrenamiento de la aptitud</string>\r\n          </keyword>\r\n          <keyword>\r\n            <string language=\"x-mt-es\">ejercicio</string>\r\n          </keyword>\r\n          <keyword>\r\n            <string language=\"x-mt-es\">m\u00fasculos</string>\r\n          </keyword>\r\n        </general>\r\n        <lifeCycle>\r\n          <contribute>\r\n            <role>\r\n              <source>LRE.roleValues</source>\r\n              <value>publisher</value>\r\n            </role>\r\n            <entity>BEGIN:VCARD\r\nVERSION:3.0\r\nN:MSU\r\nFN:MSU\r\nORG:MSU\r\nEND:VCARD</entity>\r\n          </contribute>\r\n        </lifeCycle>\r\n        <educational>\r\n          <learningResourceType>\r\n            <source>LRE.learningResourceTypeValues</source>\r\n            <value>image</value>\r\n          </learningResourceType>\r\n          <typicalAgeRange>\r\n            <string language=\"x-t-lre\">7-18</string>\r\n          </typicalAgeRange>\r\n        </educational>\r\n        <rights>\r\n          <cost>\r\n            <source>costValues</source>\r\n            <value>no</value>\r\n          </cost>\r\n          <copyrightAndOtherRestrictions>\r\n            <source>copyrightAndOtherRestrictionsValues</source>\r\n            <value>yes</value>\r\n          </copyrightAndOtherRestrictions>\r\n          <description>\r\n            <string language=\"x-t-cc-url\">http://creativecommons.org/licenses/by-nc-sa/3.0/</string>\r\n            <string language=\"en\">Creative Commons Attribution-Noncommercial-Share Alike 3.0</string>\r\n          </description>\r\n        </rights>\r\n        <classification>\r\n          <purpose>\r\n            <source>purposeValues</source>\r\n            <value>discipline</value>\r\n          </purpose>\r\n          <taxonPath>\r\n            <source>\r\n              <string language=\"x-none\">LRE-0001</string>\r\n            </source>\r\n            <taxon>\r\n              <id>632</id>\r\n              <entry>\r\n                <string language=\"en\">image</string>\r\n                <string language=\"sv\">bild</string>\r\n              </entry>\r\n            </taxon>\r\n          </taxonPath>\r\n        </classification>\r\n        <metaMetadata>\r\n          <identifier>\r\n            <catalog>oai</catalog>\r\n            <entry>oai:spindeln.iml.umu.se:526350-1</entry>\r\n          </identifier>\r\n          <identifier>\r\n            <catalog>IML-MMB</catalog>\r\n            <entry>526350-1</entry>\r\n          </identifier>\r\n          <contribute>\r\n            <entity>BEGIN:VCARD\r\nVERSION:3.0\r\nN:Iselow;Mikael\r\nFN:Mikael Iselow\r\nORG:MMB\r\nEND:VCARD</entity>\r\n            <role>\r\n              <source>LRE.roleMetaValues</source>\r\n              <value>creator</value>\r\n            </role>\r\n            <date>\r\n              <dateTime>2008-07-03T01:40:40.0Z</dateTime>\r\n            </date>\r\n          </contribute>\r\n          <language>sv</language>\r\n          <contribute>\r\n            <entity>BEGIN:VCARD\r\nFN:Myndigheten f\u00f6r skolutveckling\r\nN:Myndigheten f\u00f6r skolutveckling\r\nORG:Myndigheten f\u00f6r skolutveckling\r\nVERSION:3.0\r\nEND:VCARD</entity>\r\n            <role>\r\n              <value>provider</value>\r\n              <source>ASPECTv1.0</source>\r\n            </role>\r\n            <date>\r\n              <dateTime>2010-04-26T05:44:36.40Z</dateTime>\r\n            </date>\r\n          </contribute>\r\n        </metaMetadata>\r\n      </lom>\r\n    </metadata>\r\n  </description>\r\n  <manifestation>\r\n    <identifier>\r\n      <catalog>IML-MMB</catalog>\r\n      <entry>526350</entry>\r\n    </identifier>\r\n    <name>\r\n      <vocabularyID>LRE.manifestationNameValues</vocabularyID>\r\n      <value>experience</value>\r\n    </name>\r\n    <parameter>\r\n      <vocabularyID>MIME</vocabularyID>\r\n      <value>image/jpeg</value>\r\n    </parameter>\r\n    <item>\r\n      <location>\r\n        <uri>http://vix.iml.umu.se/mmb/526350.jpg</uri>\r\n      </location>\r\n    </item>\r\n  </manifestation>\r\n</expression>\r\n", 
    "resource_data_type": "metadata", 
    "resource_locator": "http://vix.iml.umu.se/mmb/526350.jpg"
}